x_wr_timezone.py
x_wr_timezone-2.0.0.dist-info/LICENSE
x_wr_timezone-2.0.0.dist-info/METADATA
x_wr_timezone-2.0.0.dist-info/WHEEL
x_wr_timezone-2.0.0.dist-info/entry_points.txt
x_wr_timezone-2.0.0.dist-info/top_level.txt
x_wr_timezone-2.0.0.dist-info/zip-safe
x_wr_timezone-2.0.0.dist-info/RECORD
