Metadata-Version: 2.1
Name: x-wr-timezone
Version: 2.0.0
Summary: Repair Google Calendar - This Python module and program makes ICS/iCalendar files using X-WR-TIMEZONE compatible with the RFC 5545 standard.
Home-page: https://github.com/niccokunzmann/x-wr-timezone
Author: Nicco Kunzmann
Author-email: niccokunzmann@rambler.ru
License: LGPL-3.0-or-later
Keywords: icalendar
Platform: UNKNOWN
Classifier: Intended Audience :: Developers
Classifier: License :: OSI Approved :: GNU Lesser General Public License v3 or later (LGPLv3+)
Classifier: Topic :: Software Development :: Libraries :: Python Modules
Classifier: Topic :: Utilities
Classifier: Intended Audience :: Developers
Classifier: Natural Language :: English
Classifier: Operating System :: OS Independent
Classifier: Programming Language :: Python :: 3.9
Classifier: Programming Language :: Python :: 3.10
Classifier: Programming Language :: Python :: 3.11
Classifier: Programming Language :: Python :: 3.12
Classifier: Programming Language :: Python :: 3.13
Classifier: Development Status :: 5 - Production/Stable
License-File: LICENSE
Requires-Dist: icalendar>=6.1.0
Requires-Dist: tzdata
Requires-Dist: click
